{
"meta":{"test_sets":[],"test_metrics":[],"learn_metrics":[{"best_value":"Min","name":"Logloss"}],"launch_mode":"Train","parameters":"","iteration_count":500,"learn_sets":["learn"],"name":"experiment"},
"iterations":[
{"learn":[0.6388299857],"iteration":0,"passed_time":0.8618427378,"remaining_time":430.0595261},
{"learn":[0.5753104723],"iteration":1,"passed_time":1.565265197,"remaining_time":389.751034},
{"learn":[0.5269573656],"iteration":2,"passed_time":2.212348286,"remaining_time":366.512366},
{"learn":[0.480700507],"iteration":3,"passed_time":2.891127136,"remaining_time":358.4997649},
{"learn":[0.4425465161],"iteration":4,"passed_time":3.559375491,"remaining_time":352.3781736},
{"learn":[0.4099586793],"iteration":5,"passed_time":4.177813562,"remaining_time":343.9733166},
{"learn":[0.3882905827],"iteration":6,"passed_time":4.866765597,"remaining_time":342.7593485},
{"learn":[0.3685704688],"iteration":7,"passed_time":5.473646722,"remaining_time":336.6292734},
{"learn":[0.3470521641],"iteration":8,"passed_time":6.160457249,"remaining_time":336.0871677},
{"learn":[0.3346547345],"iteration":9,"passed_time":6.823930653,"remaining_time":334.372602},
{"learn":[0.3206311176],"iteration":10,"passed_time":7.481426106,"remaining_time":332.5833969},
{"learn":[0.3084342903],"iteration":11,"passed_time":8.165319292,"remaining_time":332.0563179},
{"learn":[0.2939857583],"iteration":12,"passed_time":8.837327815,"remaining_time":331.0598958},
{"learn":[0.2865998832],"iteration":13,"passed_time":9.544905373,"remaining_time":331.3445722},
{"learn":[0.2765227654],"iteration":14,"passed_time":10.19816556,"remaining_time":329.7406865},
{"learn":[0.2646604271],"iteration":15,"passed_time":10.883866,"remaining_time":329.2369466},
{"learn":[0.2565865988],"iteration":16,"passed_time":11.54260023,"remaining_time":327.9456419},
{"learn":[0.2497172726],"iteration":17,"passed_time":12.31323388,"remaining_time":329.7210407},
{"learn":[0.24368052],"iteration":18,"passed_time":12.98860755,"remaining_time":328.8168543},
{"learn":[0.2375673544],"iteration":19,"passed_time":13.68880641,"remaining_time":328.5313539},
{"learn":[0.2308895031],"iteration":20,"passed_time":14.36925047,"remaining_time":327.7557607},
{"learn":[0.2264795996],"iteration":21,"passed_time":15.03520968,"remaining_time":326.6741012},
{"learn":[0.2224172545],"iteration":22,"passed_time":15.75196939,"remaining_time":326.6821477},
{"learn":[0.2170422302],"iteration":23,"passed_time":16.49585927,"remaining_time":327.1678754},
{"learn":[0.2122087946],"iteration":24,"passed_time":17.10926671,"remaining_time":325.0760675},
{"learn":[0.2091306616],"iteration":25,"passed_time":17.71583884,"remaining_time":322.9733697},
{"learn":[0.2062051348],"iteration":26,"passed_time":18.35381817,"remaining_time":321.5317035},
{"learn":[0.2029712028],"iteration":27,"passed_time":18.99231401,"remaining_time":320.1561504},
{"learn":[0.2002745854],"iteration":28,"passed_time":19.65375134,"remaining_time":319.2040304},
{"learn":[0.1975394481],"iteration":29,"passed_time":20.29238531,"remaining_time":317.9140366},
{"learn":[0.1950174569],"iteration":30,"passed_time":20.90840586,"remaining_time":316.3239467},
{"learn":[0.1933278889],"iteration":31,"passed_time":21.56361627,"remaining_time":315.367888},
{"learn":[0.1918185054],"iteration":32,"passed_time":22.18645583,"remaining_time":313.9719658},
{"learn":[0.190441593],"iteration":33,"passed_time":22.80990453,"remaining_time":312.629868},
{"learn":[0.1888604272],"iteration":34,"passed_time":23.42631857,"remaining_time":311.2353753},
{"learn":[0.1874151058],"iteration":35,"passed_time":24.07201704,"remaining_time":310.261553},
{"learn":[0.1864627292],"iteration":36,"passed_time":24.71397301,"remaining_time":309.2586353},
{"learn":[0.1849886827],"iteration":37,"passed_time":25.38238387,"remaining_time":308.5963512},
{"learn":[0.1840385453],"iteration":38,"passed_time":25.95912945,"remaining_time":306.8502225},
{"learn":[0.1833141762],"iteration":39,"passed_time":26.55696308,"remaining_time":305.4050755},
{"learn":[0.1818613504],"iteration":40,"passed_time":27.20835271,"remaining_time":304.6008267},
{"learn":[0.181134135],"iteration":41,"passed_time":27.87680348,"remaining_time":303.9899046},
{"learn":[0.1800757775],"iteration":42,"passed_time":28.54074052,"remaining_time":303.3283353},
{"learn":[0.1791441997],"iteration":43,"passed_time":29.23388164,"remaining_time":302.9693189},
{"learn":[0.1786284984],"iteration":44,"passed_time":29.83819045,"remaining_time":301.697259},
{"learn":[0.1778096873],"iteration":45,"passed_time":30.44882773,"remaining_time":300.5166911},
{"learn":[0.1774140355],"iteration":46,"passed_time":31.04581797,"remaining_time":299.2288413},
{"learn":[0.1770528075],"iteration":47,"passed_time":31.62524772,"remaining_time":297.804416},
{"learn":[0.1767054418],"iteration":48,"passed_time":32.2576594,"remaining_time":296.9021304},
{"learn":[0.1763976991],"iteration":49,"passed_time":32.82942175,"remaining_time":295.4647958},
{"learn":[0.1761363052],"iteration":50,"passed_time":33.36228851,"remaining_time":293.7189714},
{"learn":[0.1758701115],"iteration":51,"passed_time":33.93875342,"remaining_time":292.395414},
{"learn":[0.1756577978],"iteration":52,"passed_time":34.47889362,"remaining_time":290.7936877},
{"learn":[0.1754415944],"iteration":53,"passed_time":35.00081906,"remaining_time":289.0808389},
{"learn":[0.1752370076],"iteration":54,"passed_time":35.51831401,"remaining_time":287.3754497},
{"learn":[0.1750672783],"iteration":55,"passed_time":36.06906844,"remaining_time":285.9761855},
{"learn":[0.17488429],"iteration":56,"passed_time":36.63911644,"remaining_time":284.7566418},
{"learn":[0.1744221934],"iteration":57,"passed_time":37.23685841,"remaining_time":283.7705417},
{"learn":[0.1740223281],"iteration":58,"passed_time":37.83124318,"remaining_time":282.7725126},
{"learn":[0.1735955886],"iteration":59,"passed_time":38.47940619,"remaining_time":282.182312},
{"learn":[0.1732361375],"iteration":60,"passed_time":39.07448271,"remaining_time":281.2081625},
{"learn":[0.1729232152],"iteration":61,"passed_time":39.62782498,"remaining_time":279.9514087},
{"learn":[0.1728175782],"iteration":62,"passed_time":40.17343424,"remaining_time":278.6633455},
{"learn":[0.1723525951],"iteration":63,"passed_time":40.80092061,"remaining_time":277.9562716},
{"learn":[0.1722477267],"iteration":64,"passed_time":41.33966715,"remaining_time":276.6577725},
{"learn":[0.172035203],"iteration":65,"passed_time":41.92062711,"remaining_time":275.6598813},
{"learn":[0.1719529101],"iteration":66,"passed_time":42.4386796,"remaining_time":274.2678846},
{"learn":[0.17164416],"iteration":67,"passed_time":43.02533143,"remaining_time":273.3373997},
{"learn":[0.1714287267],"iteration":68,"passed_time":43.60124349,"remaining_time":272.3497963},
{"learn":[0.1713540461],"iteration":69,"passed_time":44.08672136,"remaining_time":270.8184312},
{"learn":[0.1711538066],"iteration":70,"passed_time":44.6797279,"remaining_time":269.9662432},
{"learn":[0.1710990197],"iteration":71,"passed_time":45.22466705,"remaining_time":268.8355208},
{"learn":[0.1709504485],"iteration":72,"passed_time":45.8256977,"remaining_time":268.0489441},
{"learn":[0.1708998124],"iteration":73,"passed_time":46.37109936,"remaining_time":266.9471396},
{"learn":[0.1708500704],"iteration":74,"passed_time":46.85234898,"remaining_time":265.4966442},
{"learn":[0.1707754733],"iteration":75,"passed_time":47.45330723,"remaining_time":264.7395035},
{"learn":[0.1707340172],"iteration":76,"passed_time":48.10621966,"remaining_time":264.2718301},
{"learn":[0.1706640541],"iteration":77,"passed_time":48.6884772,"remaining_time":263.4171459},
{"learn":[0.1705013628],"iteration":78,"passed_time":49.27558742,"remaining_time":262.595219},
{"learn":[0.1704641461],"iteration":79,"passed_time":49.77617329,"remaining_time":261.3249098},
{"learn":[0.1704221235],"iteration":80,"passed_time":50.40521571,"remaining_time":260.7380911},
{"learn":[0.1703810095],"iteration":81,"passed_time":50.93852005,"remaining_time":259.662212},
{"learn":[0.1703489705],"iteration":82,"passed_time":51.44890198,"remaining_time":258.4842425},
{"learn":[0.1703048799],"iteration":83,"passed_time":52.0064593,"remaining_time":257.5557984},
{"learn":[0.1702759923],"iteration":84,"passed_time":52.48600412,"remaining_time":256.2551966},
{"learn":[0.1702456862],"iteration":85,"passed_time":52.99855599,"remaining_time":255.1325835},
{"learn":[0.1702190206],"iteration":86,"passed_time":53.52442184,"remaining_time":254.0871979},
{"learn":[0.1701969191],"iteration":87,"passed_time":54.02123247,"remaining_time":252.9175884},
{"learn":[0.1701682708],"iteration":88,"passed_time":54.51615856,"remaining_time":251.7543951},
{"learn":[0.1701519488],"iteration":89,"passed_time":55.05341227,"remaining_time":250.7988781},
{"learn":[0.1701323892],"iteration":90,"passed_time":55.61057478,"remaining_time":249.9420339},
{"learn":[0.1700969258],"iteration":91,"passed_time":56.28004746,"remaining_time":249.5897757},
{"learn":[0.1700665464],"iteration":92,"passed_time":56.90927524,"remaining_time":249.0545702},
{"learn":[0.1700477021],"iteration":93,"passed_time":57.52623728,"remaining_time":248.4643866},
{"learn":[0.1700323658],"iteration":94,"passed_time":58.11620627,"remaining_time":247.7585636},
{"learn":[0.170016533],"iteration":95,"passed_time":58.78330558,"remaining_time":247.3797443},
{"learn":[0.1700035428],"iteration":96,"passed_time":59.3278272,"remaining_time":246.4857151},
{"learn":[0.1699892689],"iteration":97,"passed_time":59.87810953,"remaining_time":245.6224493},
{"learn":[0.169973794],"iteration":98,"passed_time":60.43157511,"remaining_time":244.7784002},
{"learn":[0.1699610458],"iteration":99,"passed_time":61.05825729,"remaining_time":244.2330292},
{"learn":[0.1698434548],"iteration":100,"passed_time":61.64167836,"remaining_time":243.5151452},
{"learn":[0.1698263995],"iteration":101,"passed_time":62.20293492,"remaining_time":242.7134127},
{"learn":[0.1698150827],"iteration":102,"passed_time":62.76227628,"remaining_time":241.9089678},
{"learn":[0.1698011542],"iteration":103,"passed_time":63.35886665,"remaining_time":241.2510692},
{"learn":[0.169789638],"iteration":104,"passed_time":64.0263547,"remaining_time":240.8610486},
{"learn":[0.1697686978],"iteration":105,"passed_time":64.70906607,"remaining_time":240.5223776},
{"learn":[0.1697590465],"iteration":106,"passed_time":65.31771654,"remaining_time":239.9052579},
{"learn":[0.1697463541],"iteration":107,"passed_time":65.91344101,"remaining_time":239.2413785},
{"learn":[0.1697377589],"iteration":108,"passed_time":66.43472875,"remaining_time":238.3117334},
{"learn":[0.1697300898],"iteration":109,"passed_time":67.10006129,"remaining_time":237.9002173},
{"learn":[0.1697191302],"iteration":110,"passed_time":67.58372649,"remaining_time":236.8474739},
{"learn":[0.1697105897],"iteration":111,"passed_time":68.20876666,"remaining_time":236.2946559},
{"learn":[0.1696975575],"iteration":112,"passed_time":68.76465427,"remaining_time":235.5037274},
{"learn":[0.1696861915],"iteration":113,"passed_time":69.33098312,"remaining_time":234.7522762},
{"learn":[0.1696672628],"iteration":114,"passed_time":69.90809481,"remaining_time":234.0401435},
{"learn":[0.1696587095],"iteration":115,"passed_time":70.54895216,"remaining_time":233.5413589},
{"learn":[0.1696507969],"iteration":116,"passed_time":71.16147453,"remaining_time":232.947391},
{"learn":[0.1696295773],"iteration":117,"passed_time":71.69550176,"remaining_time":232.0989972},
{"learn":[0.1696228915],"iteration":118,"passed_time":72.31691055,"remaining_time":231.5356548},
{"learn":[0.1696153752],"iteration":119,"passed_time":72.9505237,"remaining_time":231.0099917},
{"learn":[0.1695998204],"iteration":120,"passed_time":73.50567569,"remaining_time":230.2367859},
{"learn":[0.1695940426],"iteration":121,"passed_time":74.10386927,"remaining_time":229.600513},
{"learn":[0.1695870618],"iteration":122,"passed_time":74.71042372,"remaining_time":228.9904857},
{"learn":[0.1695796854],"iteration":123,"passed_time":75.20625517,"remaining_time":228.0447737},
{"learn":[0.169569591],"iteration":124,"passed_time":75.71027314,"remaining_time":227.1308194},
{"learn":[0.1695563033],"iteration":125,"passed_time":76.33040439,"remaining_time":226.5680257},
{"learn":[0.1695468156],"iteration":126,"passed_time":76.94612015,"remaining_time":225.9913607},
{"learn":[0.1695393071],"iteration":127,"passed_time":77.55080846,"remaining_time":225.3820371},
{"learn":[0.169528539],"iteration":128,"passed_time":78.20529761,"remaining_time":224.9160109},
{"learn":[0.169522684],"iteration":129,"passed_time":78.70494508,"remaining_time":224.0063821},
{"learn":[0.169517429],"iteration":130,"passed_time":79.22655969,"remaining_time":223.1648895},
{"learn":[0.169511512],"iteration":131,"passed_time":79.85403388,"remaining_time":222.6233672},
{"learn":[0.1695043538],"iteration":132,"passed_time":80.38790813,"remaining_time":221.8222728},
{"learn":[0.1694928941],"iteration":133,"passed_time":80.98552846,"remaining_time":221.1992792},
{"learn":[0.1694874257],"iteration":134,"passed_time":81.53187328,"remaining_time":220.4380278},
{"learn":[0.1694813785],"iteration":135,"passed_time":82.07083817,"remaining_time":219.6601845},
{"learn":[0.1694753552],"iteration":136,"passed_time":82.68511296,"remaining_time":219.0853723},
{"learn":[0.1694697921],"iteration":137,"passed_time":83.28955365,"remaining_time":218.4841915},
{"learn":[0.1694621197],"iteration":138,"passed_time":83.98356359,"remaining_time":218.115586},
{"learn":[0.1694558395],"iteration":139,"passed_time":84.58160317,"remaining_time":217.495551},
{"learn":[0.1694490126],"iteration":140,"passed_time":85.09711276,"remaining_time":216.6656985},
{"learn":[0.1693740072],"iteration":141,"passed_time":85.67036277,"remaining_time":215.9858442},
{"learn":[0.1693698248],"iteration":142,"passed_time":86.17905424,"remaining_time":215.1463102},
{"learn":[0.169364093],"iteration":143,"passed_time":86.7124724,"remaining_time":214.3725012},
{"learn":[0.1693601944],"iteration":144,"passed_time":87.32750126,"remaining_time":213.8018134},
{"learn":[0.1693548389],"iteration":145,"passed_time":87.94231389,"remaining_time":213.2299939},
{"learn":[0.1693492421],"iteration":146,"passed_time":88.4405136,"remaining_time":212.3775599},
{"learn":[0.1693445665],"iteration":147,"passed_time":88.91727152,"remaining_time":211.478916},
{"learn":[0.1693396679],"iteration":148,"passed_time":89.55295622,"remaining_time":210.9603197},
{"learn":[0.169335089],"iteration":149,"passed_time":90.17830751,"remaining_time":210.4160508},
{"learn":[0.1693306931],"iteration":150,"passed_time":90.76940183,"remaining_time":209.7915314},
{"learn":[0.1693262663],"iteration":151,"passed_time":91.24193098,"remaining_time":208.8959999},
{"learn":[0.169320772],"iteration":152,"passed_time":91.766463,"remaining_time":208.123939},
{"learn":[0.169314767],"iteration":153,"passed_time":92.26737599,"remaining_time":207.3020266},
{"learn":[0.169310431],"iteration":154,"passed_time":92.88996819,"remaining_time":206.7550905},
{"learn":[0.1693057303],"iteration":155,"passed_time":93.35178779,"remaining_time":205.8526602},
{"learn":[0.1693007885],"iteration":156,"passed_time":93.90826764,"remaining_time":205.1626484},
{"learn":[0.1692963652],"iteration":157,"passed_time":94.45797032,"remaining_time":204.4596573},
{"learn":[0.1692917575],"iteration":158,"passed_time":94.97629714,"remaining_time":203.6913039},
{"learn":[0.1692880553],"iteration":159,"passed_time":95.48265353,"remaining_time":202.9006388},
{"learn":[0.1692839891],"iteration":160,"passed_time":96.00589021,"remaining_time":202.1490483},
{"learn":[0.1692795314],"iteration":161,"passed_time":96.50903303,"remaining_time":201.3583529},
{"learn":[0.1692751337],"iteration":162,"passed_time":97.0925569,"remaining_time":200.7373722},
{"learn":[0.1692712044],"iteration":163,"passed_time":97.62071115,"remaining_time":200.0034082},
{"learn":[0.1692627378],"iteration":164,"passed_time":98.25222019,"remaining_time":199.4817804},
{"learn":[0.1691616763],"iteration":165,"passed_time":98.84385339,"remaining_time":198.8785966},
{"learn":[0.1691558048],"iteration":166,"passed_time":99.442895,"remaining_time":198.2903236},
{"learn":[0.1691489928],"iteration":167,"passed_time":100.0534593,"remaining_time":197.7246933},
{"learn":[0.1691443659],"iteration":168,"passed_time":100.6861609,"remaining_time":197.2018891},
{"learn":[0.1691410217],"iteration":169,"passed_time":101.2760338,"remaining_time":196.5946538},
{"learn":[0.1691372272],"iteration":170,"passed_time":101.8940782,"remaining_time":196.041823},
{"learn":[0.1691336806],"iteration":171,"passed_time":102.4903185,"remaining_time":195.4466539},
{"learn":[0.1691294392],"iteration":172,"passed_time":102.9965914,"remaining_time":194.6814185},
{"learn":[0.1691222878],"iteration":173,"passed_time":103.6786636,"remaining_time":194.2485306},
{"learn":[0.169118105],"iteration":174,"passed_time":104.164674,"remaining_time":193.4486803},
{"learn":[0.1691139452],"iteration":175,"passed_time":104.7816665,"remaining_time":192.8935224},
{"learn":[0.1691096479],"iteration":176,"passed_time":105.3077849,"remaining_time":192.1718334},
{"learn":[0.1691063115],"iteration":177,"passed_time":106.0009845,"remaining_time":191.75459},
{"learn":[0.1690921187],"iteration":178,"passed_time":106.6415848,"remaining_time":191.2399369},
{"learn":[0.1690874089],"iteration":179,"passed_time":107.1664705,"remaining_time":190.5181698},
{"learn":[0.1690840512],"iteration":180,"passed_time":107.658634,"remaining_time":189.7409075},
{"learn":[0.1690798351],"iteration":181,"passed_time":108.2546241,"remaining_time":189.1481894},
{"learn":[0.1690725697],"iteration":182,"passed_time":108.8522919,"remaining_time":188.5583417},
{"learn":[0.1690657989],"iteration":183,"passed_time":109.3493612,"remaining_time":187.7956421},
{"learn":[0.1690613798],"iteration":184,"passed_time":109.9531905,"remaining_time":187.2175947},
{"learn":[0.1690575437],"iteration":185,"passed_time":110.4965931,"remaining_time":186.5372594},
{"learn":[0.1690539824],"iteration":186,"passed_time":111.1151553,"remaining_time":185.9841904},
{"learn":[0.1690497828],"iteration":187,"passed_time":111.8317912,"remaining_time":185.5931854},
{"learn":[0.1690460407],"iteration":188,"passed_time":112.380913,"remaining_time":184.9230896},
{"learn":[0.1690430629],"iteration":189,"passed_time":113.1136096,"remaining_time":184.5537841},
{"learn":[0.1690390571],"iteration":190,"passed_time":113.9421504,"remaining_time":184.3357302},
{"learn":[0.1690358098],"iteration":191,"passed_time":114.6495509,"remaining_time":183.9169878},
{"learn":[0.1690320596],"iteration":192,"passed_time":115.3625073,"remaining_time":183.5040919},
{"learn":[0.1690272135],"iteration":193,"passed_time":115.9383967,"remaining_time":182.871904},
{"learn":[0.1690241642],"iteration":194,"passed_time":116.6225358,"remaining_time":182.4096073},
{"learn":[0.1690202184],"iteration":195,"passed_time":117.135692,"remaining_time":181.6798488},
{"learn":[0.169016604],"iteration":196,"passed_time":117.7902764,"remaining_time":181.1698159},
{"learn":[0.1689652157],"iteration":197,"passed_time":118.3291083,"remaining_time":180.4817713},
{"learn":[0.1689621861],"iteration":198,"passed_time":118.9223382,"remaining_time":179.8775065},
{"learn":[0.1688943702],"iteration":199,"passed_time":119.5718959,"remaining_time":179.3578438},
{"learn":[0.1688903493],"iteration":200,"passed_time":120.2379452,"remaining_time":178.861421},
{"learn":[0.1688870528],"iteration":201,"passed_time":120.7373829,"remaining_time":178.1175252},
{"learn":[0.16888293],"iteration":202,"passed_time":121.1711913,"remaining_time":177.2800188},
{"learn":[0.1688789553],"iteration":203,"passed_time":121.9228704,"remaining_time":176.9076943},
{"learn":[0.1688759662],"iteration":204,"passed_time":122.6274185,"remaining_time":176.4638461},
{"learn":[0.1688727666],"iteration":205,"passed_time":123.3232306,"remaining_time":176.004999},
{"learn":[0.1688691985],"iteration":206,"passed_time":124.0217492,"remaining_time":175.5476933},
{"learn":[0.1688015928],"iteration":207,"passed_time":124.6933014,"remaining_time":175.0502116},
{"learn":[0.1687976137],"iteration":208,"passed_time":125.3074698,"remaining_time":174.4711661},
{"learn":[0.1687953621],"iteration":209,"passed_time":125.9778951,"remaining_time":173.9694742},
{"learn":[0.1687872829],"iteration":210,"passed_time":126.5285991,"remaining_time":173.3022045},
{"learn":[0.1687845349],"iteration":211,"passed_time":127.2154356,"remaining_time":172.8209691},
{"learn":[0.1687801998],"iteration":212,"passed_time":127.8707034,"remaining_time":172.2952671},
{"learn":[0.1687762976],"iteration":213,"passed_time":128.3946183,"remaining_time":171.5928076},
{"learn":[0.1687732452],"iteration":214,"passed_time":128.9210709,"remaining_time":170.895373},
{"learn":[0.168769444],"iteration":215,"passed_time":129.4405559,"remaining_time":170.1903605},
{"learn":[0.16876642],"iteration":216,"passed_time":130.0387869,"remaining_time":169.5897543},
{"learn":[0.1687626722],"iteration":217,"passed_time":130.5938997,"remaining_time":168.9333932},
{"learn":[0.1687586924],"iteration":218,"passed_time":131.1437867,"remaining_time":168.2712514},
{"learn":[0.1687548339],"iteration":219,"passed_time":131.7592922,"remaining_time":167.6936446},
{"learn":[0.1687493258],"iteration":220,"passed_time":132.3988296,"remaining_time":167.1460337},
{"learn":[0.168688734],"iteration":221,"passed_time":132.9735031,"remaining_time":166.5163688},
{"learn":[0.168684297],"iteration":222,"passed_time":133.5677994,"remaining_time":165.9115714},
{"learn":[0.1686812556],"iteration":223,"passed_time":134.1708044,"remaining_time":165.3175982},
{"learn":[0.1686777858],"iteration":224,"passed_time":134.8693174,"remaining_time":164.8402769},
{"learn":[0.1686750412],"iteration":225,"passed_time":135.4590661,"remaining_time":164.2291333},
{"learn":[0.1686721594],"iteration":226,"passed_time":136.056997,"remaining_time":163.6280184},
{"learn":[0.1686683099],"iteration":227,"passed_time":136.5609517,"remaining_time":162.9148196},
{"learn":[0.168664499],"iteration":228,"passed_time":137.21267,"remaining_time":162.3783125},
{"learn":[0.168661599],"iteration":229,"passed_time":137.8005053,"remaining_time":161.7658106},
{"learn":[0.1686589843],"iteration":230,"passed_time":138.3253101,"remaining_time":161.080123},
{"learn":[0.168651639],"iteration":231,"passed_time":138.9259333,"remaining_time":160.4834057},
{"learn":[0.168648094],"iteration":232,"passed_time":139.407676,"remaining_time":159.750427},
{"learn":[0.1686446874],"iteration":233,"passed_time":140.0031419,"remaining_time":159.1488708},
{"learn":[0.1686384455],"iteration":234,"passed_time":140.5824847,"remaining_time":158.5291849},
{"learn":[0.1686356685],"iteration":235,"passed_time":141.1308616,"remaining_time":157.8752011},
{"learn":[0.1686327513],"iteration":236,"passed_time":141.7290292,"remaining_time":157.2773615},
{"learn":[0.1686293687],"iteration":237,"passed_time":142.2944836,"remaining_time":156.6435071},
{"learn":[0.1686250173],"iteration":238,"passed_time":142.9497243,"remaining_time":156.1082763},
{"learn":[0.1686218981],"iteration":239,"passed_time":143.441895,"remaining_time":155.3953862},
{"learn":[0.1686189048],"iteration":240,"passed_time":144.0780693,"remaining_time":154.8390869},
{"learn":[0.1686162795],"iteration":241,"passed_time":144.5560066,"remaining_time":154.1134285},
{"learn":[0.1686111588],"iteration":242,"passed_time":145.0418619,"remaining_time":153.3981832},
{"learn":[0.1686078115],"iteration":243,"passed_time":145.5521274,"remaining_time":152.7104288},
{"learn":[0.168604636],"iteration":244,"passed_time":146.1915409,"remaining_time":152.1585426},
{"learn":[0.1686004032],"iteration":245,"passed_time":146.6913664,"remaining_time":151.4618173},
{"learn":[0.1685959265],"iteration":246,"passed_time":147.2629974,"remaining_time":150.8402362},
{"learn":[0.1685308907],"iteration":247,"passed_time":147.9306695,"remaining_time":150.316648},
{"learn":[0.1685272468],"iteration":248,"passed_time":148.5615239,"remaining_time":149.7547892},
{"learn":[0.1685235102],"iteration":249,"passed_time":149.0513332,"remaining_time":149.0513332},
{"learn":[0.1685206686],"iteration":250,"passed_time":149.5423648,"remaining_time":148.3507922},
{"learn":[0.1685164631],"iteration":251,"passed_time":150.2059081,"remaining_time":147.8216873},
{"learn":[0.1685132814],"iteration":252,"passed_time":150.6978614,"remaining_time":147.123999},
{"learn":[0.1685101481],"iteration":253,"passed_time":151.1878692,"remaining_time":146.4260465},
{"learn":[0.1685065795],"iteration":254,"passed_time":151.7096352,"remaining_time":145.7602377},
{"learn":[0.1685021888],"iteration":255,"passed_time":152.3029963,"remaining_time":145.1637933},
{"learn":[0.1684985873],"iteration":256,"passed_time":153.0588057,"remaining_time":144.7209719},
{"learn":[0.1684953787],"iteration":257,"passed_time":153.6473619,"remaining_time":144.1188434},
{"learn":[0.1684916307],"iteration":258,"passed_time":154.2014216,"remaining_time":143.4847205},
{"learn":[0.1684880195],"iteration":259,"passed_time":154.7751641,"remaining_time":142.8693822},
{"learn":[0.1684128703],"iteration":260,"passed_time":155.2068402,"remaining_time":142.1242713},
{"learn":[0.1684093078],"iteration":261,"passed_time":155.7267402,"remaining_time":141.4616953},
{"learn":[0.1684059169],"iteration":262,"passed_time":156.2928083,"remaining_time":140.8418083},
{"learn":[0.1684029314],"iteration":263,"passed_time":156.8841291,"remaining_time":140.2449033},
{"learn":[0.1683996053],"iteration":264,"passed_time":157.408963,"remaining_time":139.5890804},
{"learn":[0.1683962399],"iteration":265,"passed_time":158.0069822,"remaining_time":138.9986234},
{"learn":[0.1683933352],"iteration":266,"passed_time":158.5482076,"remaining_time":138.3585482},
{"learn":[0.1683905612],"iteration":267,"passed_time":159.1492709,"remaining_time":137.7710106},
{"learn":[0.168385987],"iteration":268,"passed_time":159.7453074,"remaining_time":137.1790558},
{"learn":[0.1683829064],"iteration":269,"passed_time":160.2976147,"remaining_time":136.5498199},
{"learn":[0.168379893],"iteration":270,"passed_time":160.8611917,"remaining_time":135.9306749},
{"learn":[0.1683759049],"iteration":271,"passed_time":161.4450068,"remaining_time":135.3289027},
{"learn":[0.1683733165],"iteration":272,"passed_time":161.9872417,"remaining_time":134.6926881},
{"learn":[0.1683706635],"iteration":273,"passed_time":162.5269526,"remaining_time":134.0550777},
{"learn":[0.1683681142],"iteration":274,"passed_time":163.0568945,"remaining_time":133.4101864},
{"learn":[0.1683626774],"iteration":275,"passed_time":163.6067708,"remaining_time":132.7823067},
{"learn":[0.1683035369],"iteration":276,"passed_time":164.1676486,"remaining_time":132.1638471},
{"learn":[0.168295097],"iteration":277,"passed_time":164.7673382,"remaining_time":131.5767953},
{"learn":[0.1682922598],"iteration":278,"passed_time":165.3258408,"remaining_time":130.957028},
{"learn":[0.1682891833],"iteration":279,"passed_time":165.911979,"remaining_time":130.3594121},
{"learn":[0.1682868209],"iteration":280,"passed_time":166.4933341,"remaining_time":129.7581501},
{"learn":[0.1682842291],"iteration":281,"passed_time":167.0170508,"remaining_time":129.1124719},
{"learn":[0.1682803588],"iteration":282,"passed_time":167.5678083,"remaining_time":128.4883901},
{"learn":[0.1682773118],"iteration":283,"passed_time":168.1715714,"remaining_time":127.9051388},
{"learn":[0.1682745697],"iteration":284,"passed_time":168.7482812,"remaining_time":127.3013349},
{"learn":[0.1682719759],"iteration":285,"passed_time":169.3171592,"remaining_time":126.6918604},
{"learn":[0.1682688668],"iteration":286,"passed_time":169.8831857,"remaining_time":126.0805525},
{"learn":[0.1682653061],"iteration":287,"passed_time":170.4280625,"remaining_time":125.4539905},
{"learn":[0.1682630178],"iteration":288,"passed_time":171.0084902,"remaining_time":124.8539496},
{"learn":[0.1682324116],"iteration":289,"passed_time":171.5490638,"remaining_time":124.2251841},
{"learn":[0.1682302627],"iteration":290,"passed_time":172.1071719,"remaining_time":123.6096183},
{"learn":[0.1682263171],"iteration":291,"passed_time":172.6935513,"remaining_time":123.0145845},
{"learn":[0.168223477],"iteration":292,"passed_time":173.260119,"remaining_time":122.4056131},
{"learn":[0.1682204243],"iteration":293,"passed_time":173.8326327,"remaining_time":121.8010964},
{"learn":[0.168216707],"iteration":294,"passed_time":174.2865268,"remaining_time":121.1143661},
{"learn":[0.1682125999],"iteration":295,"passed_time":174.8296368,"remaining_time":120.4906957},
{"learn":[0.1682101756],"iteration":296,"passed_time":175.3751961,"remaining_time":119.8692418},
{"learn":[0.1682072667],"iteration":297,"passed_time":175.9383912,"remaining_time":119.2602517},
{"learn":[0.1682033768],"iteration":298,"passed_time":176.5221168,"remaining_time":118.6653695},
{"learn":[0.1681993023],"iteration":299,"passed_time":177.0617012,"remaining_time":118.0411341},
{"learn":[0.1681959249],"iteration":300,"passed_time":177.580642,"remaining_time":117.4038131},
{"learn":[0.1681916965],"iteration":301,"passed_time":178.1226475,"remaining_time":116.782398},
{"learn":[0.1681888066],"iteration":302,"passed_time":178.7146602,"remaining_time":116.19402},
{"learn":[0.168185592],"iteration":303,"passed_time":179.2689476,"remaining_time":115.5812952},
{"learn":[0.1681818872],"iteration":304,"passed_time":179.800493,"remaining_time":114.9544135},
{"learn":[0.1681787137],"iteration":305,"passed_time":180.3259362,"remaining_time":114.3242864},
{"learn":[0.1681753354],"iteration":306,"passed_time":180.9471534,"remaining_time":113.7550509},
{"learn":[0.1681721678],"iteration":307,"passed_time":181.5035212,"remaining_time":113.1450522},
{"learn":[0.1681690369],"iteration":308,"passed_time":182.0487253,"remaining_time":112.5285001},
{"learn":[0.1681624752],"iteration":309,"passed_time":182.6245865,"remaining_time":111.9311982},
{"learn":[0.1681585891],"iteration":310,"passed_time":183.1742677,"remaining_time":111.3181241},
{"learn":[0.168154443],"iteration":311,"passed_time":183.7055335,"remaining_time":110.69436},
{"learn":[0.1681515163],"iteration":312,"passed_time":184.2595783,"remaining_time":110.084796},
{"learn":[0.1681477551],"iteration":313,"passed_time":184.8119784,"remaining_time":109.4746114},
{"learn":[0.1681433091],"iteration":314,"passed_time":185.3792508,"remaining_time":108.8735283},
{"learn":[0.1681401805],"iteration":315,"passed_time":185.9818772,"remaining_time":108.293245},
{"learn":[0.1681379105],"iteration":316,"passed_time":186.5357528,"remaining_time":107.6846775},
{"learn":[0.1681338778],"iteration":317,"passed_time":187.1008178,"remaining_time":107.082858},
{"learn":[0.1681305868],"iteration":318,"passed_time":187.6767925,"remaining_time":106.4874591},
{"learn":[0.1681271215],"iteration":319,"passed_time":188.1518268,"remaining_time":105.8354026},
{"learn":[0.1681227587],"iteration":320,"passed_time":188.7128068,"remaining_time":105.2323751},
{"learn":[0.1681196715],"iteration":321,"passed_time":189.2459348,"remaining_time":104.6142124},
{"learn":[0.1680772469],"iteration":322,"passed_time":189.7866129,"remaining_time":104.0007136},
{"learn":[0.1680738252],"iteration":323,"passed_time":190.3393655,"remaining_time":103.3942232},
{"learn":[0.1680703501],"iteration":324,"passed_time":190.8890922,"remaining_time":102.7864342},
{"learn":[0.168062229],"iteration":325,"passed_time":191.4419786,"remaining_time":102.1806879},
{"learn":[0.1680577417],"iteration":326,"passed_time":192.003654,"remaining_time":101.5799148},
{"learn":[0.1680543944],"iteration":327,"passed_time":192.5722076,"remaining_time":100.9829869},
{"learn":[0.1679969059],"iteration":328,"passed_time":193.0590403,"remaining_time":100.3437565},
{"learn":[0.1679928205],"iteration":329,"passed_time":193.6083488,"remaining_time":99.73763422},
{"learn":[0.1679898751],"iteration":330,"passed_time":194.1542664,"remaining_time":99.13012394},
{"learn":[0.167987439],"iteration":331,"passed_time":194.6854514,"remaining_time":98.51552961},
{"learn":[0.1679231657],"iteration":332,"passed_time":195.2512625,"remaining_time":97.9188013},
{"learn":[0.1679191924],"iteration":333,"passed_time":195.7964356,"remaining_time":97.31200094},
{"learn":[0.1679154378],"iteration":334,"passed_time":196.3638289,"remaining_time":96.71651274},
{"learn":[0.1679126802],"iteration":335,"passed_time":196.9386306,"remaining_time":96.12480778},
{"learn":[0.1679094478],"iteration":336,"passed_time":197.3734447,"remaining_time":95.46549401},
{"learn":[0.1679061758],"iteration":337,"passed_time":197.7546202,"remaining_time":94.78180021},
{"learn":[0.1679026241],"iteration":338,"passed_time":198.1444294,"remaining_time":94.10399155},
{"learn":[0.167898993],"iteration":339,"passed_time":198.5626871,"remaining_time":93.44126453},
{"learn":[0.1678955481],"iteration":340,"passed_time":198.9771262,"remaining_time":92.7781908},
{"learn":[0.1678907872],"iteration":341,"passed_time":199.4074623,"remaining_time":92.12391534},
{"learn":[0.167887717],"iteration":342,"passed_time":199.8470769,"remaining_time":91.47519263},
{"learn":[0.1678835444],"iteration":343,"passed_time":200.3209456,"remaining_time":90.84321953},
{"learn":[0.1678807051],"iteration":344,"passed_time":200.7431044,"remaining_time":90.18893095},
{"learn":[0.1678777767],"iteration":345,"passed_time":201.1967714,"remaining_time":89.55000806},
{"learn":[0.1678739808],"iteration":346,"passed_time":201.6531156,"remaining_time":88.91333341},
{"learn":[0.1678714],"iteration":347,"passed_time":202.014937,"remaining_time":88.23640927},
{"learn":[0.1678684583],"iteration":348,"passed_time":202.3333869,"remaining_time":87.54252557},
{"learn":[0.1678654015],"iteration":349,"passed_time":202.6575163,"remaining_time":86.85322127},
{"learn":[0.1678622113],"iteration":350,"passed_time":202.9885707,"remaining_time":86.1689374},
{"learn":[0.1678595206],"iteration":351,"passed_time":203.3184956,"remaining_time":85.48618565},
{"learn":[0.1678558288],"iteration":352,"passed_time":203.6477048,"remaining_time":84.80513487},
{"learn":[0.1678529715],"iteration":353,"passed_time":203.9979421,"remaining_time":84.13474446},
{"learn":[0.1678499181],"iteration":354,"passed_time":204.5232479,"remaining_time":83.53766465},
{"learn":[0.167846589],"iteration":355,"passed_time":205.0823061,"remaining_time":82.95464069},
{"learn":[0.1678434282],"iteration":356,"passed_time":205.6379934,"remaining_time":82.37040071},
{"learn":[0.1678400712],"iteration":357,"passed_time":206.1739605,"remaining_time":81.77849831},
{"learn":[0.1678361002],"iteration":358,"passed_time":206.6743623,"remaining_time":81.17293896},
{"learn":[0.1678321366],"iteration":359,"passed_time":207.2540245,"remaining_time":80.5987873},
{"learn":[0.167828127],"iteration":360,"passed_time":207.7675202,"remaining_time":79.99912829},
{"learn":[0.1678254289],"iteration":361,"passed_time":208.2336837,"remaining_time":79.38190153},
{"learn":[0.1678201322],"iteration":362,"passed_time":208.8516535,"remaining_time":78.82280037},
{"learn":[0.1678164643],"iteration":363,"passed_time":209.2752914,"remaining_time":78.19076823},
{"learn":[0.1678127202],"iteration":364,"passed_time":209.8634762,"remaining_time":77.62073776},
{"learn":[0.167809224],"iteration":365,"passed_time":210.399232,"remaining_time":77.03141281},
{"learn":[0.1678054758],"iteration":366,"passed_time":210.9440796,"remaining_time":76.44567463},
{"learn":[0.1678014904],"iteration":367,"passed_time":211.6217155,"remaining_time":75.90778927},
{"learn":[0.1677984342],"iteration":368,"passed_time":212.2643583,"remaining_time":75.3567234},
{"learn":[0.1677950482],"iteration":369,"passed_time":212.7295116,"remaining_time":74.74280136},
{"learn":[0.1677910663],"iteration":370,"passed_time":213.2060363,"remaining_time":74.13363527},
{"learn":[0.1677875552],"iteration":371,"passed_time":213.6473339,"remaining_time":73.51306112},
{"learn":[0.1677841638],"iteration":372,"passed_time":214.2032087,"remaining_time":72.93245979},
{"learn":[0.1677803341],"iteration":373,"passed_time":214.7805564,"remaining_time":72.35922488},
{"learn":[0.1677776642],"iteration":374,"passed_time":215.3133205,"remaining_time":71.77110683},
{"learn":[0.1677749672],"iteration":375,"passed_time":215.847612,"remaining_time":71.18378693},
{"learn":[0.167771535],"iteration":376,"passed_time":216.2946975,"remaining_time":70.56829652},
{"learn":[0.167768923],"iteration":377,"passed_time":216.8184678,"remaining_time":69.97844727},
{"learn":[0.167765223],"iteration":378,"passed_time":217.3904884,"remaining_time":69.40435117},
{"learn":[0.1677620638],"iteration":379,"passed_time":217.8525321,"remaining_time":68.79553646},
{"learn":[0.1677593007],"iteration":380,"passed_time":218.2888336,"remaining_time":68.17945197},
{"learn":[0.167755424],"iteration":381,"passed_time":218.8099487,"remaining_time":67.59050772},
{"learn":[0.1677525135],"iteration":382,"passed_time":219.3603362,"remaining_time":67.01085988},
{"learn":[0.1677491335],"iteration":383,"passed_time":219.9261764,"remaining_time":66.43603245},
{"learn":[0.1677455545],"iteration":384,"passed_time":220.5053871,"remaining_time":65.86524548},
{"learn":[0.1677419737],"iteration":385,"passed_time":221.0611434,"remaining_time":65.28748796},
{"learn":[0.1677385421],"iteration":386,"passed_time":221.6108049,"remaining_time":64.70806448},
{"learn":[0.1677351299],"iteration":387,"passed_time":222.1562477,"remaining_time":64.12757664},
{"learn":[0.1677323906],"iteration":388,"passed_time":222.6900546,"remaining_time":63.54394875},
{"learn":[0.1677293596],"iteration":389,"passed_time":223.2399353,"remaining_time":62.96510995},
{"learn":[0.1677260826],"iteration":390,"passed_time":223.7984015,"remaining_time":62.38881269},
{"learn":[0.1677217947],"iteration":391,"passed_time":224.3308815,"remaining_time":61.80544694},
{"learn":[0.1677184014],"iteration":392,"passed_time":224.9039187,"remaining_time":61.23338245},
{"learn":[0.1677159312],"iteration":393,"passed_time":225.4142534,"remaining_time":60.64444381},
{"learn":[0.1677138211],"iteration":394,"passed_time":225.9706069,"remaining_time":60.06813601},
{"learn":[0.1677098753],"iteration":395,"passed_time":226.5724876,"remaining_time":59.50388564},
{"learn":[0.1677062734],"iteration":396,"passed_time":227.0209017,"remaining_time":58.8996294},
{"learn":[0.1677030867],"iteration":397,"passed_time":227.5336863,"remaining_time":58.31265327},
{"learn":[0.1677000365],"iteration":398,"passed_time":228.0353319,"remaining_time":57.72322939},
{"learn":[0.1676956685],"iteration":399,"passed_time":228.573968,"remaining_time":57.143492},
{"learn":[0.1676909449],"iteration":400,"passed_time":229.1378793,"remaining_time":56.57019962},
{"learn":[0.1676887043],"iteration":401,"passed_time":229.6376329,"remaining_time":55.98131349},
{"learn":[0.1676855356],"iteration":402,"passed_time":230.168493,"remaining_time":55.40035687},
{"learn":[0.1676827663],"iteration":403,"passed_time":230.7091867,"remaining_time":54.82198496},
{"learn":[0.1676788525],"iteration":404,"passed_time":231.2696198,"remaining_time":54.24842934},
{"learn":[0.1676741444],"iteration":405,"passed_time":231.7850712,"remaining_time":53.66452387},
{"learn":[0.1676702919],"iteration":406,"passed_time":232.3576439,"remaining_time":53.09400708},
{"learn":[0.1676668904],"iteration":407,"passed_time":232.9327451,"remaining_time":52.52405036},
{"learn":[0.1676637287],"iteration":408,"passed_time":233.5286553,"remaining_time":51.95869837},
{"learn":[0.1676602237],"iteration":409,"passed_time":234.1435446,"remaining_time":51.39736346},
{"learn":[0.1676565339],"iteration":410,"passed_time":234.6918279,"remaining_time":50.82134473},
{"learn":[0.1676525653],"iteration":411,"passed_time":235.2052334,"remaining_time":50.23801102},
{"learn":[0.1676500312],"iteration":412,"passed_time":235.8051688,"remaining_time":49.6732438},
{"learn":[0.167646429],"iteration":413,"passed_time":236.3697653,"remaining_time":49.10096574},
{"learn":[0.1676428852],"iteration":414,"passed_time":236.9070034,"remaining_time":48.52312117},
{"learn":[0.1676397273],"iteration":415,"passed_time":237.4672289,"remaining_time":47.95011353},
{"learn":[0.1676034118],"iteration":416,"passed_time":237.997327,"remaining_time":47.3711706},
{"learn":[0.1675998278],"iteration":417,"passed_time":238.5610617,"remaining_time":46.79905995},
{"learn":[0.1675966928],"iteration":418,"passed_time":239.125846,"remaining_time":46.22719219},
{"learn":[0.1675937442],"iteration":419,"passed_time":239.7189332,"remaining_time":45.66074917},
{"learn":[0.1675908863],"iteration":420,"passed_time":240.456135,"remaining_time":45.12122249},
{"learn":[0.167587217],"iteration":421,"passed_time":241.0248172,"remaining_time":44.54961076},
{"learn":[0.1675843611],"iteration":422,"passed_time":241.6276651,"remaining_time":43.98423218},
{"learn":[0.167580717],"iteration":423,"passed_time":242.203652,"remaining_time":43.41386216},
{"learn":[0.1675781254],"iteration":424,"passed_time":242.8250045,"remaining_time":42.85147138},
{"learn":[0.1675749057],"iteration":425,"passed_time":243.2387607,"remaining_time":42.25274248},
{"learn":[0.1675697365],"iteration":426,"passed_time":243.7892031,"remaining_time":41.67824784},
{"learn":[0.1675670195],"iteration":427,"passed_time":244.4171352,"remaining_time":41.11690125},
{"learn":[0.167563405],"iteration":428,"passed_time":244.8079408,"remaining_time":40.51599952},
{"learn":[0.1675598066],"iteration":429,"passed_time":245.2961053,"remaining_time":39.93192411},
{"learn":[0.1675568596],"iteration":430,"passed_time":245.8535959,"remaining_time":39.35939239},
{"learn":[0.1675529099],"iteration":431,"passed_time":246.3097286,"remaining_time":38.77097579},
{"learn":[0.1675495325],"iteration":432,"passed_time":247.0223906,"remaining_time":38.22286414},
{"learn":[0.1675446913],"iteration":433,"passed_time":247.6899492,"remaining_time":37.66713513},
{"learn":[0.1675415202],"iteration":434,"passed_time":248.2493527,"remaining_time":37.09473086},
{"learn":[0.1675382882],"iteration":435,"passed_time":248.8536965,"remaining_time":36.52898297},
{"learn":[0.1675345559],"iteration":436,"passed_time":249.3685052,"remaining_time":35.95015064},
{"learn":[0.1675315366],"iteration":437,"passed_time":250.1308088,"remaining_time":35.40664417},
{"learn":[0.1675282307],"iteration":438,"passed_time":250.7026364,"remaining_time":34.83567385},
{"learn":[0.1675247738],"iteration":439,"passed_time":251.2158461,"remaining_time":34.25670628},
{"learn":[0.1675202113],"iteration":440,"passed_time":251.7753657,"remaining_time":33.6842326},
{"learn":[0.1675171817],"iteration":441,"passed_time":252.3156033,"remaining_time":33.10928731},
{"learn":[0.1675130055],"iteration":442,"passed_time":252.8670488,"remaining_time":32.53594081},
{"learn":[0.1675085947],"iteration":443,"passed_time":253.3548631,"remaining_time":31.95466742},
{"learn":[0.1675046259],"iteration":444,"passed_time":253.9210416,"remaining_time":31.38349952},
{"learn":[0.1675011993],"iteration":445,"passed_time":254.3895572,"remaining_time":30.80052934},
{"learn":[0.1674988441],"iteration":446,"passed_time":254.9833035,"remaining_time":30.23291966},
{"learn":[0.1674960599],"iteration":447,"passed_time":255.5297483,"remaining_time":29.65970293},
{"learn":[0.1674923858],"iteration":448,"passed_time":256.0691355,"remaining_time":29.08580381},
{"learn":[0.1674892627],"iteration":449,"passed_time":256.528249,"remaining_time":28.50313877},
{"learn":[0.1674871206],"iteration":450,"passed_time":257.0658849,"remaining_time":27.9295529},
{"learn":[0.1674836188],"iteration":451,"passed_time":257.6209396,"remaining_time":27.35797588},
{"learn":[0.1674801621],"iteration":452,"passed_time":258.0711492,"remaining_time":26.77559385},
{"learn":[0.1674771285],"iteration":453,"passed_time":258.5348172,"remaining_time":26.19515769},
{"learn":[0.1674737371],"iteration":454,"passed_time":259.0656519,"remaining_time":25.62187766},
{"learn":[0.1674698913],"iteration":455,"passed_time":259.5902733,"remaining_time":25.04818426},
{"learn":[0.1674662589],"iteration":456,"passed_time":260.1395419,"remaining_time":24.47702473},
{"learn":[0.1674629098],"iteration":457,"passed_time":260.6643697,"remaining_time":23.9037195},
{"learn":[0.1674600778],"iteration":458,"passed_time":261.1859607,"remaining_time":23.33033636},
{"learn":[0.1674563023],"iteration":459,"passed_time":261.6849678,"remaining_time":22.75521459},
{"learn":[0.1674524194],"iteration":460,"passed_time":262.1929342,"remaining_time":22.18118098},
{"learn":[0.1674054378],"iteration":461,"passed_time":262.6495964,"remaining_time":21.60321355},
{"learn":[0.1674014305],"iteration":462,"passed_time":263.217258,"remaining_time":21.03464049},
{"learn":[0.1673985113],"iteration":463,"passed_time":263.64316,"remaining_time":20.45507276},
{"learn":[0.1673957673],"iteration":464,"passed_time":264.0804061,"remaining_time":19.87701981},
{"learn":[0.1673926015],"iteration":465,"passed_time":264.5836141,"remaining_time":19.30438386},
{"learn":[0.1673896191],"iteration":466,"passed_time":265.0948934,"remaining_time":18.7326156},
{"learn":[0.1673851477],"iteration":467,"passed_time":265.630509,"remaining_time":18.16276984},
{"learn":[0.1673823616],"iteration":468,"passed_time":266.1620385,"remaining_time":17.59279998},
{"learn":[0.1673788232],"iteration":469,"passed_time":266.6940059,"remaining_time":17.02302165},
{"learn":[0.1673760799],"iteration":470,"passed_time":267.2258862,"remaining_time":16.45339852},
{"learn":[0.1673737179],"iteration":471,"passed_time":267.8056732,"remaining_time":15.88677722},
{"learn":[0.1673711086],"iteration":472,"passed_time":268.4480555,"remaining_time":15.32367336},
{"learn":[0.1673677445],"iteration":473,"passed_time":269.078335,"remaining_time":14.75957112},
{"learn":[0.1673649312],"iteration":474,"passed_time":269.6396062,"remaining_time":14.19155822},
{"learn":[0.167361818],"iteration":475,"passed_time":270.1290016,"remaining_time":13.61994966},
{"learn":[0.167358818],"iteration":476,"passed_time":270.6349565,"remaining_time":13.04948428},
{"learn":[0.1673550186],"iteration":477,"passed_time":271.1012697,"remaining_time":12.47746429},
{"learn":[0.1673515529],"iteration":478,"passed_time":271.5021704,"remaining_time":11.90301791},
{"learn":[0.1673484086],"iteration":479,"passed_time":271.8730588,"remaining_time":11.32804412},
{"learn":[0.1673459418],"iteration":480,"passed_time":272.2418138,"remaining_time":10.75383464},
{"learn":[0.1673427412],"iteration":481,"passed_time":272.7551902,"remaining_time":10.18587847},
{"learn":[0.1673400021],"iteration":482,"passed_time":273.1474445,"remaining_time":9.613885209},
{"learn":[0.1673368152],"iteration":483,"passed_time":273.5419231,"remaining_time":9.042708203},
{"learn":[0.1673342583],"iteration":484,"passed_time":273.9511313,"remaining_time":8.472715401},
{"learn":[0.1673322667],"iteration":485,"passed_time":274.3509446,"remaining_time":7.903113631},
{"learn":[0.1673285708],"iteration":486,"passed_time":274.7640798,"remaining_time":7.33456476},
{"learn":[0.167325602],"iteration":487,"passed_time":275.1507271,"remaining_time":6.766001487},
{"learn":[0.1673228631],"iteration":488,"passed_time":275.4308555,"remaining_time":6.195786116},
{"learn":[0.1673198043],"iteration":489,"passed_time":275.6361246,"remaining_time":5.625227032},
{"learn":[0.1673164882],"iteration":490,"passed_time":275.8425806,"remaining_time":5.056177649},
{"learn":[0.1673128267],"iteration":491,"passed_time":276.0565628,"remaining_time":4.488724598},
{"learn":[0.1673101404],"iteration":492,"passed_time":276.2601713,"remaining_time":3.922558214},
{"learn":[0.1673068714],"iteration":493,"passed_time":276.4698219,"remaining_time":3.357933059},
{"learn":[0.1673030826],"iteration":494,"passed_time":276.5959089,"remaining_time":2.79389807},
{"learn":[0.1672995418],"iteration":495,"passed_time":276.7101601,"remaining_time":2.231533549},
{"learn":[0.1672964597],"iteration":496,"passed_time":276.830203,"remaining_time":1.671007261},
{"learn":[0.1672930494],"iteration":497,"passed_time":276.9402099,"remaining_time":1.112209678},
{"learn":[0.16728999],"iteration":498,"passed_time":277.0461585,"remaining_time":0.5552027224},
{"learn":[0.167286885],"iteration":499,"passed_time":277.1542828,"remaining_time":0}
]}ing_time":0}
]}